{"note":"This file is an internal implementation detail to speed up HTML report generation. Its format can change at any time. You might be looking for the JSON report: https://coverage.rtfd.io/cmd.html#cmd-json","format":5,"version":"7.13.4","globals":"ca477c5088f31900f9ce04ee141513e8","files":{"app_py":{"hash":"f027844281a667c54cbebc47d9ec4c1f","index":{"url":"app_py.html","file":"app.py","description":"","nums":{"precision":0,"n_files":1,"n_statements":92,"n_excluded":0,"n_missing":1,"n_branches":0,"n_partial_branches":0,"n_missing_branches":0}}},"test_app_py":{"hash":"1357249a23fa663ecb20d71eecd78eca","index":{"url":"test_app_py.html","file":"test_app.py","description":"","nums":{"precision":0,"n_files":1,"n_statements":82,"n_excluded":0,"n_missing":0,"n_branches":0,"n_partial_branches":0,"n_missing_branches":0}}}}}